{
  "aiInsights": {
    "overview": "2025年10月26日群内仅1条消息，由马工提出关于腾讯未大力推广元宝的疑问，整体活跃度极低但具争议性。",
    "highlights": [
      "单日仅1条消息，发送者为马工",
      "问题聚焦腾讯战略与元宝推广",
      "凌晨1点为唯一活跃时段",
      "关键词集中于‘元宝’‘微信’‘马化腾’"
    ],
    "opportunities": [
      "可引导讨论AI产品落地策略",
      "澄清元宝与腾讯产品矩阵关系"
    ],
    "risks": [
      "低活跃度影响群价值",
      "高管年龄等敏感话题易引发争议"
    ],
    "actions": [
      "安排专人回应元宝推广策略疑问",
      "策划AI产品话题提升参与度",
      "设定群聊规范避免人身讨论"
    ],
    "spotlight": "‘腾讯为什么没有全力推荐元宝？’——折射用户对AI产品落地的期待与困惑"
  },
  "date": "2025-10-26",
  "keyword": "",
  "summary": {
    "totalMessages": 1,
    "uniqueSenders": 1,
    "topSenders": [
      {
        "key": "马工",
        "count": 1
      }
    ],
    "topLinks": [],
    "hourlyHistogram": [
      0,
      1,
      0,
      0,
      0,
      0,
      0,
      0,
      0,
      0,
      0,
      0,
      0,
      0,
      0,
      0,
      0,
      0,
      0,
      0,
      0,
      0,
      0,
      0
    ],
    "keywords": [
      {
        "key": "不是老",
        "count": 1
      },
      {
        "key": "为什",
        "count": 1
      },
      {
        "key": "为什么",
        "count": 1
      },
      {
        "key": "么没",
        "count": 1
      },
      {
        "key": "么没有",
        "count": 1
      },
      {
        "key": "什么没",
        "count": 1
      },
      {
        "key": "信和",
        "count": 1
      },
      {
        "key": "元宝",
        "count": 1
      },
      {
        "key": "元宝给",
        "count": 1
      },
      {
        "key": "全力",
        "count": 1
      },
      {
        "key": "全力推",
        "count": 1
      },
      {
        "key": "力推",
        "count": 1
      },
      {
        "key": "力推荐",
        "count": 1
      },
      {
        "key": "化腾",
        "count": 1
      },
      {
        "key": "化腾是",
        "count": 1
      },
      {
        "key": "宝给",
        "count": 1
      },
      {
        "key": "宝给所",
        "count": 1
      },
      {
        "key": "微信",
        "count": 1
      },
      {
        "key": "微信和",
        "count": 1
      },
      {
        "key": "所有",
        "count": 1
      }
    ],
    "peakHour": 1,
    "highlights": [
      "消息 1 条，活跃 1 人；峰值 01:00-01:59",
      "Top 发送者：马工(1)"
    ],
    "topics": [],
    "imageCount": 0,
    "groupVibes": {
      "score": 17,
      "activity": 0.05,
      "sentiment": 0.5,
      "infoDensity": 0,
      "controversy": 1,
      "tone": "氛围偏冷",
      "reasons": [
        "消息量偏低，讨论热度不足",
        "争议度高，需要关注共识"
      ]
    },
    "replyDebt": {
      "outstanding": [
        {
          "questioner": "马工",
          "question": "马化腾是不是老了？腾讯为什么没有全力推荐元宝给所有微信和qq用户？",
          "askedAt": "2025-10-26T01:14:32+08:00"
        }
      ],
      "resolved": null,
      "avgResponseMinutes": 0,
      "bestResponseHours": null
    }
  },
  "talker": "27587714869@chatroom"
}
